loopsim/__init__.py
loopsim/__main__.py
loopsim/analyze.py
loopsim/batch_analyze.py
loopsim/cli.py
loopsim/common.py
loopsim/simulate.py
loopsim/validate.py
loopsim/visualize.py
loopsim-0.6.1.dist-info/LICENSE
loopsim-0.6.1.dist-info/METADATA
loopsim-0.6.1.dist-info/WHEEL
loopsim-0.6.1.dist-info/entry_points.txt
loopsim-0.6.1.dist-info/RECORD
