Metadata-Version: 2.1
Name: loopsim
Version: 0.6.1
Summary: Loopsim: Enrichment Analysis of Chromosome Conformation Capture with Fast Empirical Distribution Simulation
Home-page: https://github.com/CutaneousBioinf/loopsim
License: MIT
Author: Gideon Shaked
Author-email: gshaked@umich.edu
Maintainer: Gideon Shaked
Maintainer-email: gshaked@umich.edu
Requires-Python: >=3.8
Classifier: Environment :: Console
Classifier: License :: OSI Approved :: MIT License
Classifier: Natural Language :: English
Classifier: Programming Language :: Python
Classifier: Programming Language :: Python :: 3
Classifier: Programming Language :: Python :: 3.8
Classifier: Programming Language :: Python :: 3.9
Classifier: Programming Language :: Python :: 3.10
Classifier: Programming Language :: Python :: 3.11
Classifier: Programming Language :: Python :: 3.12
Classifier: Programming Language :: Python :: 3 :: Only
Requires-Dist: click (>=8.1.3,<8.2.0)
Requires-Dist: detect-delimiter (>=0.1.1,<0.2.0)
Requires-Dist: numpy (>=1.24.4,<1.25.0)
Requires-Dist: pandas (>=2.0.2,<2.1.0)
Requires-Dist: scipy (>=1.9.3,<1.10.0)
Requires-Dist: seaborn (>=0.12.2,<0.13.0)
Project-URL: Repository, https://github.com/CutaneousBioinf/loopsim
